syscolourtoolkitsV1/__init__.py
syscolourtoolkitsV1-1.1.0.dist-info/METADATA
syscolourtoolkitsV1-1.1.0.dist-info/WHEEL
syscolourtoolkitsV1-1.1.0.dist-info/top_level.txt
syscolourtoolkitsV1-1.1.0.dist-info/RECORD
