Metadata-Version: 2.1
Name: syscolourtoolkitsV1
Version: 1.1.0
Summary: trjpwqewuhotbomuzg
Home-page: UNKNOWN
Author: richardXZQ89
Author-email: richardXZQ89@gmail.com
License: UNKNOWN
Keywords: python
Platform: UNKNOWN
Classifier: Operating System :: Microsoft :: Windows
